shadowshell/__init__.py
shadowshell/backup/bootstrap.py
shadowshell/backup/test.py
shadowshell/boot/__init__.py
shadowshell/boot/starter.py
shadowshell/config/__init__.py
shadowshell/config/configurator.py
shadowshell/db/__init__.py
shadowshell/db/db_starter.py
shadowshell/file/__init__.py
shadowshell/file/file_util.py
shadowshell/logging/__init__.py
shadowshell/logging/console_logger.py
shadowshell/logging/logger.py
shadowshell/logging/logger_factory.py
shadowshell/logging/logging_constants.py
shadowshell/logging/logging_logger.py
shadowshell/model/__init__.py
shadowshell/model/dataset.py
shadowshell/model/tree.py
shadowshell/monitor/__init__.py
shadowshell/monitor/monitor.py
shadowshell/request/__init__.py
shadowshell/request/request.py
shadowshell/serialize/__init__.py
shadowshell/serialize/serializable.py
shadowshell/serialize/serializer.py
shadowshell/serialize/serializer_factory.py
shadowshell/serialize/serializer_json.py
shadowshell/test/__init__.py
shadowshell/test/test.py
shadowshell/xyz/__init__.py
shadowshell/xyz/xyz.py
shadowshell-202509020003.dist-info/METADATA
shadowshell-202509020003.dist-info/WHEEL
shadowshell-202509020003.dist-info/top_level.txt
shadowshell-202509020003.dist-info/RECORD
