Metadata-Version: 2.4
Name: shadowshell
Version: 202509020003
Summary: www.shadowshell.xyz
Author-email: shadowshell <shadowshell@foxmail.com>
License: MIT
Classifier: Programming Language :: Python :: 3
Classifier: Operating System :: OS Independent
Requires-Python: >=3.6
Requires-Dist: configparser
Requires-Dist: sqlalchemy
Requires-Dist: pymysql
Requires-Dist: pandas
Requires-Dist: openpyxl
